<?xml version="1.0" encoding="UTF-8"?>
<results title="frequencies">
 <result title="frequency" word="species" count="89"/>
 <result title="frequency" word="[]." count="61"/>
 <result title="frequency" word="OpenUrl" count="54"/>
 <result title="frequency" word="suitability" count="54"/>
 <result title="frequency" word="human" count="49"/>
 <result title="frequency" word="SDM" count="48"/>
 <result title="frequency" word="CrossRef" count="47"/>
 <result title="frequency" word="distribution" count="44"/>
 <result title="frequency" word="triatomine" count="36"/>
 <result title="frequency" word="environmental" count="34"/>
 <result title="frequency" word="density" count="32"/>
 <result title="frequency" word="Chagas" count="30"/>
 <result title="frequency" word="population" count="27"/>
 <result title="frequency" word="spatial" count="20"/>
 <result title="frequency" word="geographical" count="19"/>
 <result title="frequency" word="models" count="19"/>
 <result title="frequency" word="Human" count="18"/>
 <result title="frequency" word="disease" count="18"/>
 <result title="frequency" word="variables" count="18"/>
 <result title="frequency" word="clim" count="16"/>
 <result title="frequency" word="obtained" count="16"/>
 <result title="frequency" word="SDMs" count="15"/>
 <result title="frequency" word="Science" count="15"/>
 <result title="frequency" word="projections" count="15"/>
 <result title="frequency" word="Triatoma" count="14"/>
 <result title="frequency" word="ecological" count="14"/>
 <result title="frequency" word="maps" count="14"/>
 <result title="frequency" word="using" count="14"/>
 <result title="frequency" word="Bio" count="13"/>
 <result title="frequency" word="Ecol" count="13"/>
 <result title="frequency" word="Web" count="13"/>
 <result title="frequency" word="data" count="13"/>
 <result title="frequency" word="infectious" count="13"/>
 <result title="frequency" word="accumulated" count="12"/>
 <result title="frequency" word="model" count="12"/>
 <result title="frequency" word="species." count="12"/>
 <result title="frequency" word="used" count="12"/>
 <result title="frequency" word="vectors" count="12"/>
 <result title="frequency" word="climatic" count="11"/>
 <result title="frequency" word="diseases" count="11"/>
 <result title="frequency" word="relevant" count="11"/>
 <result title="frequency" word="vector" count="11"/>
 <result title="frequency" word="(i.e.," count="10"/>
 <result title="frequency" word="area" count="10"/>
 <result title="frequency" word="different" count="10"/>
 <result title="frequency" word="interactions" count="10"/>
 <result title="frequency" word="map" count="10"/>
 <result title="frequency" word="patterns" count="10"/>
 <result title="frequency" word="performance" count="10"/>
 <result title="frequency" word="Global" count="9"/>
 <result title="frequency" word="Maxent" count="9"/>
 <result title="frequency" word="binary" count="9"/>
 <result title="frequency" word="considered" count="9"/>
 <result title="frequency" word="influence" count="9"/>
 <result title="frequency" word="interaction" count="9"/>
 <result title="frequency" word="new" count="9"/>
 <result title="frequency" word="niche" count="9"/>
 <result title="frequency" word="occurrence" count="9"/>
 <result title="frequency" word="variable" count="9"/>
 <result title="frequency" word="climate" count="8"/>
 <result title="frequency" word="higher" count="8"/>
 <result title="frequency" word="modeled" count="8"/>
 <result title="frequency" word="points" count="8"/>
 <result title="frequency" word="predictor" count="8"/>
 <result title="frequency" word="records" count="8"/>
 <result title="frequency" word="results" count="8"/>
 <result title="frequency" word="Biogeogr" count="7"/>
 <result title="frequency" word="Brazilian" count="7"/>
 <result title="frequency" word="Inst" count="7"/>
 <result title="frequency" word="So," count="7"/>
 <result title="frequency" word="bias" count="7"/>
 <result title="frequency" word="biotic" count="7"/>
 <result title="frequency" word="control" count="7"/>
 <result title="frequency" word="epidemiologically" count="7"/>
 <result title="frequency" word="focal" count="7"/>
 <result title="frequency" word="populations" count="7"/>
 <result title="frequency" word="precipitation" count="7"/>
 <result title="frequency" word="present" count="7"/>
 <result title="frequency" word="software" count="7"/>
 <result title="frequency" word="species," count="7"/>
 <result title="frequency" word="values" count="7"/>
 <result title="frequency" word="Cruz" count="6"/>
 <result title="frequency" word="Disease" count="6"/>
 <result title="frequency" word="Figure" count="6"/>
 <result title="frequency" word="Mem" count="6"/>
 <result title="frequency" word="Oswaldo" count="6"/>
 <result title="frequency" word="Species" count="6"/>
 <result title="frequency" word="analysis" count="6"/>
 <result title="frequency" word="areas" count="6"/>
 <result title="frequency" word="distributions" count="6"/>
 <result title="frequency" word="humans" count="6"/>
 <result title="frequency" word="importance" count="6"/>
 <result title="frequency" word="models." count="6"/>
 <result title="frequency" word="niche-based" count="6"/>
 <result title="frequency" word="pROC" count="6"/>
 <result title="frequency" word="permutation" count="6"/>
 <result title="frequency" word="produced" count="6"/>
 <result title="frequency" word="related" count="6"/>
 <result title="frequency" word="research" count="6"/>
 <result title="frequency" word="scales" count="6"/>
 <result title="frequency" word="studies" count="6"/>
 <result title="frequency" word="triatomines" count="6"/>
 <result title="frequency" word="./S-." count="5"/>
 <result title="frequency" word="./j.-...x." count="5"/>
 <result title="frequency" word="Anderson" count="5"/>
 <result title="frequency" word="Glob" count="5"/>
 <result title="frequency" word="However," count="5"/>
 <result title="frequency" word="Modell" count="5"/>
 <result title="frequency" word="Peterson" count="5"/>
 <result title="frequency" word="Results" count="5"/>
 <result title="frequency" word="Trop" count="5"/>
 <result title="frequency" word="accounting" count="5"/>
 <result title="frequency" word="affect" count="5"/>
 <result title="frequency" word="analyzed" count="5"/>
 <result title="frequency" word="available" count="5"/>
 <result title="frequency" word="background" count="5"/>
 <result title="frequency" word="difference" count="5"/>
 <result title="frequency" word="disease." count="5"/>
 <result title="frequency" word="dynamics" count="5"/>
 <result title="frequency" word="ecology" count="5"/>
 <result title="frequency" word="epidemiological" count="5"/>
 <result title="frequency" word="geographic" count="5"/>
 <result title="frequency" word="group" count="5"/>
 <result title="frequency" word="high" count="5"/>
 <result title="frequency" word="important" count="5"/>
 <result title="frequency" word="inclusion" count="5"/>
 <result title="frequency" word="infestans" count="5"/>
 <result title="frequency" word="maped" count="5"/>
 <result title="frequency" word="mean" count="5"/>
 <result title="frequency" word="observed" count="5"/>
 <result title="frequency" word="overlap" count="5"/>
 <result title="frequency" word="possible" count="5"/>
 <result title="frequency" word="quarter," count="5"/>
 <result title="frequency" word="range" count="5"/>
 <result title="frequency" word="space" count="5"/>
 <result title="frequency" word="studied" count="5"/>
 <result title="frequency" word="./-." count="4"/>
 <result title="frequency" word="./j.ecolmodel...." count="4"/>
 <result title="frequency" word="Abstract" count="4"/>
 <result title="frequency" word="Brazil," count="4"/>
 <result title="frequency" word="Brazil." count="4"/>
 <result title="frequency" word="Ceccarelli" count="4"/>
 <result title="frequency" word="Despite" count="4"/>
 <result title="frequency" word="Distribution" count="4"/>
 <result title="frequency" word="Download" count="4"/>
 <result title="frequency" word="Human." count="4"/>
 <result title="frequency" word="Med" count="4"/>
 <result title="frequency" word="Moreover," count="4"/>
 <result title="frequency" word="Pearson" count="4"/>
 <result title="frequency" word="Phillips" count="4"/>
 <result title="frequency" word="Rabinovich" count="4"/>
 <result title="frequency" word="Rev" count="4"/>
 <result title="frequency" word="Rhodnius" count="4"/>
 <result title="frequency" word="SDM&amp;lt;;sub&amp;gt;;Human&amp;lt;;/sub&amp;gt;;" count="4"/>
 <result title="frequency" word="South" count="4"/>
 <result title="frequency" word="algorithm" count="4"/>
 <result title="frequency" word="aspect" count="4"/>
 <result title="frequency" word="assessment" count="4"/>
 <result title="frequency" word="case" count="4"/>
 <result title="frequency" word="critical" count="4"/>
 <result title="frequency" word="differences" count="4"/>
 <result title="frequency" word="disease," count="4"/>
 <result title="frequency" word="focused" count="4"/>
 <result title="frequency" word="global" count="4"/>
 <result title="frequency" word="greater" count="4"/>
 <result title="frequency" word="highly" count="4"/>
 <result title="frequency" word="impact" count="4"/>
 <result title="frequency" word="knowledge" count="4"/>
 <result title="frequency" word="levels" count="4"/>
 <result title="frequency" word="linear" count="4"/>
 <result title="frequency" word="lower" count="4"/>
 <result title="frequency" word="macroecological" count="4"/>
 <result title="frequency" word="macroecology" count="4"/>
 <result title="frequency" word="main" count="4"/>
 <result title="frequency" word="measure" count="4"/>
 <result title="frequency" word="omission" count="4"/>
 <result title="frequency" word="package" count="4"/>
 <result title="frequency" word="performed" count="4"/>
 <result title="frequency" word="predictions" count="4"/>
 <result title="frequency" word="provided" count="4"/>
 <result title="frequency" word="rely" count="4"/>
 <result title="frequency" word="represent" count="4"/>
 <result title="frequency" word="richness" count="4"/>
 <result title="frequency" word="sampling" count="4"/>
 <result title="frequency" word="temperature" count="4"/>
 <result title="frequency" word="transmission" count="4"/>
 <result title="frequency" word="vectors." count="4"/>
 <result title="frequency" word="work" count="4"/>
</results>
