<?xml version="1.0" encoding="UTF-8"?>
<snippetsTree>
 <snippets file="testsearch250/10_1101_673913v1/results/search/funders/results.xml">
  <result pre="albopictus. Elife. 2015; 4: e08347. OpenUrl CrossRef PubMed 8. ↵" exact="World Health Organization." post="World Malaria Report 2018. Geneva.: World Health Organization; 2018"/>
  <result pre="8. ↵ World Health Organization. World Malaria Report 2018. Geneva.:" exact="World Health Organization;" post="2018 Nov. 9. ↵ Siraj A , Santos-Vega M"/>
  <result pre="the African highlands: past, present and future. Bulletin of the" exact="World Health Organization." post="1998; 76: 33. OpenUrl PubMed Web of Science 14."/>
  <result pre="the East African highlands: temperature trends revisited. Proceedings of the" exact="National Academy of Sciences." post="2006; 103: 5829– 5834. OpenUrl Abstract / FREE Full"/>
  <result pre="recent decades in an East African highland. Proceedings of the" exact="Royal Society" post="B: Biological Sciences. 2010; 278: 1661– 1669. OpenUrl 19."/>
  <result pre="reveals the role of El Niño 2015. Proceedings of the" exact="National Academy of Sciences." post="2017; 114: 119– 124. OpenUrl Abstract / FREE Full"/>
  <result pre="spatial scales links zoonotic malaria to deforestation. Proceedings of the" exact="Royal Society" post="B. 2019; 286: 20182351. OpenUrl 42. ↵ Potts M"/>
 </snippets>
</snippetsTree>
