<?xml version="1.0" encoding="UTF-8"?>
<snippetsTree>
 <snippets file="testsearch250/10_1101_630947v1/results/search/funders/results.xml">
  <result pre="Lepidoptera and Biodiversity, Florida Museum of Natural History at the" exact="University of Florida" post="(MGCL). Statistical Analyses Generalized linear models were used to"/>
  <result pre="a study case in an Ecuadorian dry forest. Master’s Thesis," exact="University of Florida." post="↵ Checa, M.F. , Barragán, A. , Rodríguez, J."/>
  <result pre="climate warming on terrestrial ectotherms across latitude. Proceedings of the" exact="National Academy of Sciences" post="of the United States of America, 105, 6668– 6672."/>
  <result pre="and reproductive biology of Heliconius butterflies . Proceedings of the" exact="National Academy of Sciences," post="69, 1403– 1407. OpenUrl Abstract / FREE Full Text"/>
  <result pre="OpenUrl CrossRef ↵ Hilbe, J. ( 1994) Generalized linear models." exact="American Statistical Association," post="48, 255– 265. OpenUrl ↵ Hoffmann, J.P. ( 2004)"/>
  <result pre="&amp;amp;; Wolfinger, R. ( 1996) SAS System for Mixed Models." exact="SAS Institute," post="NC, US. ↵ McLaughlin, J. , Hellmann, J. ,"/>
  <result pre="I. ( 2010) What drives community dynamics? Proceedings of the" exact="Royal Society" post="of London, 276, 2923– 2929. OpenUrl ↵ Novotny, V."/>
  <result pre="abundance explains butterfly biodiversity in island communities. Proceedings of the" exact="National Academy of Sciences" post="of the United States of America, 104, 10524– 10529."/>
 </snippets>
</snippetsTree>
